{
	"animations": [
		{
			"loop": false,
			"offsets": [
				1,
				0
			],
			"fps": 24,
			"anim": "idle",
			"indices": [],
			"name": "Pico Idle Dance"
		},
		{
			"loop": false,
			"offsets": [
				25,
				2
			],
			"fps": 24,
			"anim": "singLEFT",
			"indices": [],
			"name": "Pico Note Right0"
		},
		{
			"loop": false,
			"offsets": [
				42,
				-7
			],
			"fps": 24,
			"anim": "singRIGHT",
			"indices": [],
			"name": "Pico NOTE LEFT0"
		},
		{
			"loop": false,
			"offsets": [
				-19,
				27
			],
			"fps": 24,
			"anim": "singUP",
			"indices": [],
			"name": "pico Up note0"
		},
		{
			"loop": false,
			"offsets": [
				190,
				-80
			],
			"fps": 24,
			"anim": "singDOWN",
			"indices": [],
			"name": "Pico Down Note0"
		},
		{
			"loop": false,
			"offsets": [
				-26,
				-7
			],
			"anim": "reload",
			"fps": 24,
			"name": "Pico Gun Charge0",
			"indices": []
		},
		{
			"loop": false,
			"offsets": [
				5,
				14
			],
			"anim": "shoot",
			"fps": 24,
			"name": "Pico Fire",
			"indices": []
		}
	],
	"no_antialiasing": false,
	"image": "characters/gopico/pico-d1",
	"position": [
		0,
		300
	],
	"healthicon": "pico-d1",
	"flip_x": true,
	"healthbar_colors": [
		183,
		216,
		85
	],
	"camera_position": [
		0,
		0
	],
	"sing_duration": 4,
	"scale": 1
}